gui_gen/__init__.py
gui_gen/app/__init__.py
gui_gen/app/app.py
gui_gen/app/templates/app.jinja2
gui_gen/arguments/__init__.py
gui_gen/arguments/boolean.py
gui_gen/arguments/choice.py
gui_gen/arguments/datetime.py
gui_gen/arguments/file.py
gui_gen/arguments/generic.py
gui_gen/arguments/numeric.py
gui_gen/arguments/text.py
gui_gen/arguments/templates/Boolean.jinja2
gui_gen/arguments/templates/Choice.jinja2
gui_gen/arguments/templates/Date.jinja2
gui_gen/arguments/templates/DateTime.jinja2
gui_gen/arguments/templates/File.jinja2
gui_gen/arguments/templates/Float.jinja2
gui_gen/arguments/templates/Int.jinja2
gui_gen/arguments/templates/TextBox.jinja2
gui_gen/arguments/templates/generic.jinja2
gui_gen/eel_setup/__init__.py
gui_gen/eel_setup/expose.py
gui_gen/meta/__init__.py
gui_gen/meta/meta.py
gui_gen/meta/templates/__main__.jinja2
gui_gen/meta/templates/__main__js.jinja2
gui_gen/meta/templates/style.css
gui_gen/process/__init__.py
gui_gen/process/process.py
gui_gen/process/templates/process.jinja2
GuiGen-1.2.0.dist-info/METADATA
GuiGen-1.2.0.dist-info/WHEEL
GuiGen-1.2.0.dist-info/top_level.txt
GuiGen-1.2.0.dist-info/RECORD
