Metadata-Version: 2.1
Name: GuiGen
Version: 1.2.0
Summary: GuiGen
Home-page: https://github.com/FilipM13/GuiGen
Author: Filip Matejko
Author-email: matejkofilip@gmail.com
Requires-Python: >=3.9
Requires-Dist: eel
Requires-Dist: jinja2
Requires-Dist: lxml
Requires-Dist: bs4
Requires-Dist: easygui
